hypotonic/__init__.py
hypotonic/command.py
hypotonic/context.py
hypotonic/request.py
hypotonic-0.0.15.dist-info/LICENSE
hypotonic-0.0.15.dist-info/WHEEL
hypotonic-0.0.15.dist-info/METADATA
hypotonic-0.0.15.dist-info/RECORD
