Metadata-Version: 2.1
Name: hypotonic
Version: 0.0.15
Summary: Fast asynchronous web scraper with minimalist API.
Home-page: https://github.com/mscavnicky/hypotonic
License: MIT
Author: Martin Scavnicky
Author-email: martin.scavnicky@gmail.com
Requires-Python: >=3.6,<4.0
Classifier: Development Status :: 2 - Pre-Alpha
Classifier: License :: OSI Approved :: MIT License
Classifier: Operating System :: OS Independent
Classifier: Programming Language :: Python :: 3
Classifier: Programming Language :: Python :: 3.6
Classifier: Programming Language :: Python :: 3.7
Classifier: Programming Language :: Python :: 3.8
Classifier: Topic :: Text Processing :: Markup :: HTML
Requires-Dist: aiohttp (>=3.0.9)
Requires-Dist: backoff (>=1.8.0)
Requires-Dist: beautifulsoup4 (>=4.7.1)
Requires-Dist: html5lib (>=1.0.1)
Requires-Dist: jsonpath-ng (>=1.5.1)
Requires-Dist: more_itertools (>=6.0.0)
Requires-Dist: validators (>=0.18.0)
